Metadata-Version: 2.1
Name: SequaGUI
Version: 0.0.9
Summary: Advanced Combobox with searching built-in
Author: Sequa Inc
Author-email: soberonlineemail@gmail.com
Keywords: python,Tkinter,GUI,package
